.gitignore
CMakeLists.txt
NOTES.txt
README.md
TODO.txt
WINDOWS_ANACONDA_BUILD.txt
pyproject.toml
setup.cfg
setup.py
setupcmd.bat
setupcmd.sh
.github/workflows/push-to-public.yml
.github/workflows/push-to-pypi.yml
.github/workflows/push_tags_to_public.yml
cmake/FindEigen3.cmake
doc/DocumentationGuide.md
doc/archive_docs.sh
doc/ProgramRef/Makefile
doc/ProgramRef/ReferenceGenerationHTMLDoxfile
doc/ProgramRef/ReferenceGenerationPDFDoxfile
doc/ProgramRef/make.bat
doc/UsersGuide/Makefile
doc/UsersGuide/make.bat
doc/UsersGuide/source/GraphicsProjection_Channel.png
doc/UsersGuide/source/GraphicsProjection_Specimen.png
doc/UsersGuide/source/ProbePositioner_Screenshot.png
doc/UsersGuide/source/Synthetic_Probe_Impedance_Image.png
doc/UsersGuide/source/about.rst
doc/UsersGuide/source/concepts.rst
doc/UsersGuide/source/conf.py
doc/UsersGuide/source/examples.rst
doc/UsersGuide/source/index.rst
doc/UsersGuide/source/installation.rst
doc/UsersGuide/source/plate_and_probe.png
doc/UsersGuide/source/usage.rst
doc/misc/Projection_simplified.pdf
doc/misc/Projection_simplified.xopp
example/custom_geometrystruct_demo.py
example/dgs_x3d_extract.py
example/different_locking_processes.py
example/opencl_example.cpp
example/opencl_example.py
example/opencl_example2.py
example/osg_example.cpp
example/png_viewer_qt.cpp
python/README.txt
python/pyproject_assign_git_root.py
python/spatialnde2/manual_positioner_in_transaction.dpi
python/spatialnde2/project_probe_tip_data_in_transaction.dpi
python/spatialnde2/quatpy.py
python/spatialnde2/recdb.dpi
python/spatialnde2/recdb_gui.dpi
snde/Brighten.png
snde/Darken.png
snde/LessContrast.png
snde/MoreContrast.png
snde/NumPy_BGRtoGray16.cpp
snde/NumPy_BGRtoGray16.hpp
snde/NumPy_BGRtoGray16.i
snde/NumPy_BGRtoRGBA.cpp
snde/NumPy_BGRtoRGBA.hpp
snde/NumPy_BGRtoRGBA.i
snde/ResetIntensity.png
snde/ZoomIn.png
snde/ZoomOut.png
snde/__init__.pxd
snde/accumulate_once.cpp
snde/accumulate_once.hpp
snde/accumulate_once.i
snde/allocator.cpp
snde/allocator.h
spatialnde2.egg-info/PKG-INFO
spatialnde2.egg-info/SOURCES.txt
spatialnde2.egg-info/dependency_links.txt
spatialnde2.egg-info/not-zip-safe
spatialnde2.egg-info/top_level.txt
