Metadata-Version: 2.2
Name: spatialnde2
Version: 0.8.1
Summary: spatialnde2
Home-page: http://thermal.cnde.iastate.edu/spatialnde2.xhtml
Author: Stephen D. Holland
Classifier: Development Status :: 3 - Alpha
Classifier: License :: OSI Approved :: BSD License
Requires-Python: >=3.8
Dynamic: author
Dynamic: home-page
Dynamic: summary
